{"content":[{"id":"69e35972","settings":{"layout":"full_width","height":"min-height","custom_height":{"unit":"px","size":631,"sizes":[]},"stretch_section":"section-stretched","structure":"20","background_background":"classic","background_color":"#FFFFFF"},"elements":[{"id":"1f4e521c","settings":{"_column_size":50,"_inline_size":null,"background_background":"classic"},"elements":[{"id":"10923bef","settings":{"video_type":"hosted","youtube_url":"https:\/\/www.youtube.com\/watch?v=XHOmBV4js_E","vimeo_url":"https:\/\/vimeo.com\/235215203","dailymotion_url":"https:\/\/www.dailymotion.com\/video\/x6tqhqb","hosted_url":{"url":"https:\/\/elmanicomiotattoo.es\/wp-content\/uploads\/2023\/05\/IMG_6851.mov","id":204,"size":"","alt":"","source":"library"},"autoplay":"yes","mute":"yes","loop":"yes","controls":""},"elements":[],"isInner":false,"widgetType":"video","elType":"widget"}],"isInner":false,"elType":"column"},{"id":"6326fd10","settings":{"_column_size":50,"_inline_size":null},"elements":[{"id":"35dbd79","settings":{"title":"SERMUNO","align":"center","title_color":"#000000","typography_typography":"custom","typography_font_family":"Oswald","typography_font_weight":"600"},"elements":[],"isInner":false,"widgetType":"heading","elType":"widget"},{"id":"6a47bd1e","settings":{"width":{"unit":"%","size":22,"sizes":[]},"align":"center","text":"Separador"},"elements":[],"isInner":false,"widgetType":"divider","elType":"widget"},{"id":"45774fae","settings":{"editor":"<p>Un tatuador especializado en el arte del lettering. Con una pasi\u00f3n desbordante por el grafiti, el hip hop y todo el g\u00e9nero urbano, Sermuno ha encontrado su voz a trav\u00e9s de la creaci\u00f3n de letras y tipograf\u00edas \u00fanicas en el mundo del tatuaje.<\/p><p>Con un estilo audaz y en\u00e9rgico, Sermuno combina su amor por la cultura urbana con su destreza en el dise\u00f1o de letras para crear tatuajes impactantes y llenos de personalidad. Sus dise\u00f1os de lettering capturan la esencia del movimiento grafiti y del hip hop, aportando un toque callejero y aut\u00e9ntico a cada pieza.<\/p><p dir=\"auto\">Si eres un amante del lettering, Sermuno es el tatuador perfecto para ti. Su habilidad para plasmar tus palabras, nombres o frases favoritas en un estilo \u00fanico y vibrante te permitir\u00e1 llevar contigo un mensaje significativo y personalizado.<\/p>","text_columns":"1","column_gap":{"unit":"px","size":0,"sizes":[]},"align":"justify","_margin":{"unit":"px","top":"16","right":"44","bottom":"44","left":"44","isLinked":false}},"elements":[],"isInner":false,"widgetType":"text-editor","elType":"widget"},{"id":"6b5732d0","settings":{"text":"PEDIR CITA","align":"right","size":"lg","button_text_color":"#FFFFFF","background_color":"#000000","hover_color":"#00CF02","button_background_hover_color":"#000000","border_border":"none","border_radius":{"unit":"px","top":"0","right":"0","bottom":"0","left":"0","isLinked":true},"_element_width":"initial","_element_custom_width":{"unit":"%","size":79.267},"link":{"url":"www.elmanicomiotattoo.com\/contacto","is_external":"","nofollow":"","custom_attributes":""},"typography_typography":"custom","typography_font_family":"Oswald","typography_font_weight":"500"},"elements":[],"isInner":false,"widgetType":"button","elType":"widget"},{"id":"22cefc32","settings":{"social_icon_list":[{"social_icon":{"value":"fab fa-instagram","library":"fa-brands"},"_id":"fff6c16","link":{"url":"https:\/\/www.instagram.com\/sermunotattoo","is_external":"true","nofollow":"","custom_attributes":""}}],"align":"right","icon_color":"custom","hover_secondary_color":"#02FF4D","_element_width":"initial","_element_custom_width":{"unit":"%","size":10.285}},"elements":[],"isInner":false,"widgetType":"social-icons","elType":"widget"}],"isInner":false,"elType":"column"}],"isInner":false,"elType":"section"},{"id":"5013acc4","settings":{"layout":"full_width","height":"min-height","stretch_section":"section-stretched","background_overlay_background":"classic","background_overlay_image":{"url":"https:\/\/elmanicomiotattoo.es\/wp-content\/uploads\/2023\/01\/people-3292901_1920.jpeg","id":22,"alt":"","source":"library"},"background_overlay_position":"center center","background_overlay_attachment":"fixed","background_overlay_size":"cover","background_overlay_opacity":{"unit":"px","size":0.55,"sizes":[]},"custom_height":{"unit":"px","size":490,"sizes":[]},"animation":"fadeInRight"},"elements":[{"id":"4f1ab47e","settings":{"_column_size":100,"_inline_size":null},"elements":[{"id":"4dbaf0d7","settings":{"carousel":[{"id":184,"url":"https:\/\/elmanicomiotattoo.es\/wp-content\/uploads\/2023\/05\/image00003-2.jpeg"},{"id":185,"url":"https:\/\/elmanicomiotattoo.es\/wp-content\/uploads\/2023\/05\/image00004-2.jpeg"},{"id":186,"url":"https:\/\/elmanicomiotattoo.es\/wp-content\/uploads\/2023\/05\/image00005-2.jpeg"},{"id":187,"url":"https:\/\/elmanicomiotattoo.es\/wp-content\/uploads\/2023\/05\/image00006-2.jpeg"},{"id":188,"url":"https:\/\/elmanicomiotattoo.es\/wp-content\/uploads\/2023\/05\/image00007-2.jpeg"},{"id":189,"url":"https:\/\/elmanicomiotattoo.es\/wp-content\/uploads\/2023\/05\/image00008-2.jpeg"},{"id":190,"url":"https:\/\/elmanicomiotattoo.es\/wp-content\/uploads\/2023\/05\/image00009-2.jpeg"},{"id":191,"url":"https:\/\/elmanicomiotattoo.es\/wp-content\/uploads\/2023\/05\/image00010-2.jpeg"},{"id":192,"url":"https:\/\/elmanicomiotattoo.es\/wp-content\/uploads\/2023\/05\/image00011-1.jpeg"},{"id":193,"url":"https:\/\/elmanicomiotattoo.es\/wp-content\/uploads\/2023\/05\/image00012.jpeg"},{"id":194,"url":"https:\/\/elmanicomiotattoo.es\/wp-content\/uploads\/2023\/05\/image00013.jpeg"},{"id":195,"url":"https:\/\/elmanicomiotattoo.es\/wp-content\/uploads\/2023\/05\/image00014.jpeg"},{"id":196,"url":"https:\/\/elmanicomiotattoo.es\/wp-content\/uploads\/2023\/05\/image00015.jpeg"},{"id":197,"url":"https:\/\/elmanicomiotattoo.es\/wp-content\/uploads\/2023\/05\/image00001-2.jpeg"},{"id":198,"url":"https:\/\/elmanicomiotattoo.es\/wp-content\/uploads\/2023\/05\/image00002-2.jpeg"}],"thumbnail_size":"portfolio-square","slides_to_show_mobile":"1"},"elements":[],"isInner":false,"widgetType":"image-carousel","elType":"widget"}],"isInner":false,"elType":"column"}],"isInner":false,"elType":"section"},{"id":"6d3e8e22","settings":[],"elements":[{"id":"14f6cbe4","settings":{"_column_size":100,"_inline_size":null},"elements":[{"id":"7eb388e2","settings":{"space":{"unit":"px","size":10,"sizes":[]}},"elements":[],"isInner":false,"widgetType":"spacer","elType":"widget"}],"isInner":false,"elType":"column"}],"isInner":false,"elType":"section"},{"id":"6a26427e","settings":{"layout":"full_width","height":"min-height","custom_height":{"unit":"px","size":199,"sizes":[]},"stretch_section":"section-stretched","animation":"fadeInLeft"},"elements":[{"id":"6aefbe6a","settings":{"_column_size":100,"_inline_size":null},"elements":[{"id":"c248070","settings":{"carousel":[{"id":199,"url":"https:\/\/elmanicomiotattoo.es\/wp-content\/uploads\/2023\/05\/image00008-3.jpeg"},{"id":200,"url":"https:\/\/elmanicomiotattoo.es\/wp-content\/uploads\/2023\/05\/image00012-1.jpeg"},{"id":201,"url":"https:\/\/elmanicomiotattoo.es\/wp-content\/uploads\/2023\/05\/image00013-1.jpeg"},{"id":202,"url":"https:\/\/elmanicomiotattoo.es\/wp-content\/uploads\/2023\/05\/image00015-1.jpeg"},{"id":203,"url":"https:\/\/elmanicomiotattoo.es\/wp-content\/uploads\/2023\/05\/image00002-3.jpeg"}],"thumbnail_size":"medium","slides_to_show":"4","link_to":"file","open_lightbox":"yes","image_spacing":"custom","image_spacing_custom":{"unit":"px","size":0,"sizes":[]},"slides_to_show_mobile":"1"},"elements":[],"isInner":false,"widgetType":"image-carousel","elType":"widget"}],"isInner":false,"elType":"column"}],"isInner":false,"elType":"section"},{"id":"3569b909","settings":[],"elements":[{"id":"7d747d11","settings":{"_column_size":100,"_inline_size":null},"elements":[{"id":"3807be65","settings":{"space":{"unit":"px","size":10,"sizes":[]}},"elements":[],"isInner":false,"widgetType":"spacer","elType":"widget"}],"isInner":false,"elType":"column"}],"isInner":false,"elType":"section"},{"id":"148451bc","settings":{"layout":"full_width","height":"min-height","stretch_section":"section-stretched","structure":"30","background_overlay_background":"classic","background_overlay_image":{"url":"https:\/\/elmanicomiotattoo.es\/wp-content\/uploads\/2023\/01\/people-3292901_1920.jpeg","id":22,"alt":"","source":"library"},"background_overlay_position":"center center","background_overlay_attachment":"fixed","background_overlay_size":"cover","background_overlay_opacity":{"unit":"px","size":0.55,"sizes":[]},"animation":"fadeInUp","custom_height_mobile":{"unit":"px","size":156,"sizes":[]}},"elements":[{"id":"15d5f318","settings":{"_column_size":33,"_inline_size":null},"elements":[],"isInner":false,"elType":"column"},{"id":"667a7c2c","settings":{"_column_size":33,"_inline_size":null},"elements":[{"id":"57738d99","settings":{"text":"PEDIR CITA","align":"center","typography_typography":"custom","typography_font_family":"Oswald","typography_font_weight":"500","button_text_color":"#FFFFFF","background_color":"#000000","hover_color":"#00FF09"},"elements":[],"isInner":false,"widgetType":"button","elType":"widget"}],"isInner":false,"elType":"column"},{"id":"17a80744","settings":{"_column_size":33,"_inline_size":null},"elements":[],"isInner":false,"elType":"column"}],"isInner":false,"elType":"section"},{"id":"1af29ad2","settings":{"animation":"fadeInDown"},"elements":[{"id":"425f4ddb","settings":{"_column_size":100,"_inline_size":null},"elements":[{"id":"38c1e3a1","settings":{"title":"Mas artistas?","align":"center","title_color":"#FFFFFF","typography_typography":"custom","typography_font_family":"Oswald","typography_font_weight":"600"},"elements":[],"isInner":false,"widgetType":"heading","elType":"widget"}],"isInner":false,"elType":"column"}],"isInner":false,"elType":"section"},{"id":"68cc3e5b","settings":{"structure":"50","animation":"fadeInUp"},"elements":[{"id":"5b442b9e","settings":{"_column_size":20,"_inline_size":null},"elements":[{"id":"3874a963","settings":{"image":{"url":"https:\/\/elmanicomiotattoo.es\/wp-content\/uploads\/2023\/05\/image00002-scaled.jpeg","id":97,"size":"","alt":"","source":"library"},"image_size":"thumbnail","caption_source":"custom","caption":"DOGO","link_to":"custom","link":{"url":"www.elmanicomiotattoo.com\/dogo\/","is_external":"","nofollow":"","custom_attributes":""},"_mask_switch":"yes"},"elements":[],"isInner":false,"widgetType":"image","elType":"widget"}],"isInner":false,"elType":"column"},{"id":"3973493b","settings":{"_column_size":20,"_inline_size":null},"elements":[{"id":"5be9f767","settings":{"image":{"url":"https:\/\/elmanicomiotattoo.es\/wp-content\/uploads\/2023\/05\/image00002-1.jpeg","id":107,"size":"","alt":"","source":"library"},"image_size":"thumbnail","caption_source":"custom","caption":"RICHI","link_to":"custom","link":{"url":"www.elmanicomiotattoo.com\/richi\/","is_external":"","nofollow":"","custom_attributes":""},"_mask_switch":"yes"},"elements":[],"isInner":false,"widgetType":"image","elType":"widget"}],"isInner":false,"elType":"column"},{"id":"b7e829d","settings":{"_column_size":20,"_inline_size":null},"elements":[{"id":"26615571","settings":{"image":{"url":"https:\/\/elmanicomiotattoo.es\/wp-content\/uploads\/2023\/05\/IMG_20220402_131917_053.webp","id":162,"size":"","alt":"","source":"library"},"image_size":"thumbnail","caption_source":"custom","caption":"SHANA","link_to":"custom","link":{"url":"www.elmanicomiotattoo.com\/shana\/","is_external":"","nofollow":"","custom_attributes":""},"_mask_switch":"yes"},"elements":[],"isInner":false,"widgetType":"image","elType":"widget"}],"isInner":false,"elType":"column"},{"id":"38539413","settings":{"_column_size":20,"_inline_size":null},"elements":[{"id":"285f8b58","settings":{"image":{"url":"https:\/\/elmanicomiotattoo.es\/wp-content\/uploads\/2023\/05\/image00008-3.jpeg","id":199,"size":"","alt":"","source":"library"},"image_size":"thumbnail","caption_source":"custom","caption":"SERMUNO","link_to":"custom","link":{"url":"www.elmanicomiotattoo.com\/sermuno\/","is_external":"","nofollow":"","custom_attributes":""},"_mask_switch":"yes"},"elements":[],"isInner":false,"widgetType":"image","elType":"widget"}],"isInner":false,"elType":"column"},{"id":"5b0bd6ee","settings":{"_column_size":20,"_inline_size":null},"elements":[{"id":"1d13bb56","settings":{"image":{"url":"https:\/\/elmanicomiotattoo.es\/wp-content\/uploads\/2023\/05\/1682781333901.jpg","id":144,"size":"","alt":"","source":"library"},"image_size":"thumbnail","caption_source":"custom","caption":"GIULIA","link_to":"custom","link":{"url":"www.elmanicomiotattoo.com\/giulia\/","is_external":"","nofollow":"","custom_attributes":""},"_mask_switch":"yes"},"elements":[],"isInner":false,"widgetType":"image","elType":"widget"}],"isInner":false,"elType":"column"}],"isInner":false,"elType":"section"}],"settings":{"template":"default"},"metadata":{"qode_page_background_image_fixed":"yes","qode_show-sidebar":"default"}}